CHANGELOG.md
MANIFEST.in
README.md
requirements.txt
requirements_dev.txt
setup.cfg
setup.py
pydeck_earthengine_layers/__init__.py
pydeck_earthengine_layers/pydeck_earthengine_layers.py
pydeck_earthengine_layers.egg-info/PKG-INFO
pydeck_earthengine_layers.egg-info/SOURCES.txt
pydeck_earthengine_layers.egg-info/dependency_links.txt
pydeck_earthengine_layers.egg-info/not-zip-safe
pydeck_earthengine_layers.egg-info/requires.txt
pydeck_earthengine_layers.egg-info/top_level.txt