Metadata-Version: 2.1
Name: pydeck-earthengine-layers
Version: 1.2.1
Summary: Pydeck wrapper for use with Google Earth Engine
Home-page: https://github.com/UnfoldedInc/earthengine-layers/blob/master/py
Author: Kyle Barron
Author-email: kyle@unfolded.ai
License: MIT license
Keywords: pydeck_earthengine_layers
Platform: UNKNOWN
Classifier: Development Status :: 4 - Beta
Classifier: Intended Audience :: Developers
Classifier: License :: OSI Approved :: MIT License
Classifier: Natural Language :: English
Classifier: Programming Language :: Python :: 3
Classifier: Programming Language :: Python :: 3.5
Classifier: Programming Language :: Python :: 3.6
Classifier: Programming Language :: Python :: 3.7
Classifier: Programming Language :: Python :: 3.8
Requires-Python: >=3.5
